josedemo/__init__.py
josedemo/cli.py
josedemo-0.1.1.dist-info/METADATA
josedemo-0.1.1.dist-info/WHEEL
josedemo-0.1.1.dist-info/entry_points.txt
josedemo-0.1.1.dist-info/top_level.txt
josedemo-0.1.1.dist-info/RECORD
