Metadata-Version: 2.1
Name: josedemo
Version: 0.1.1
Summary: Add your description here
Requires-Python: >=3.13
Requires-Dist: typer>=0.15.1
